copytruncate.py
copytruncate-0.1.1.dist-info/LICENSE
copytruncate-0.1.1.dist-info/METADATA
copytruncate-0.1.1.dist-info/WHEEL
copytruncate-0.1.1.dist-info/entry_points.txt
copytruncate-0.1.1.dist-info/top_level.txt
copytruncate-0.1.1.dist-info/RECORD
