Metadata-Version: 2.1
Name: copytruncate
Version: 0.1.1
Summary: 文件另存后清空文件，保持文件inode不变。一般可用于大日志文件的交换等场景。
Home-page: https://github.com/appstore-zencore/copytruncate
Author: zencore
Author-email: dobetter@zencore.cn
License: MIT
Keywords: copytruncate
Platform: UNKNOWN
Classifier: Development Status :: 5 - Production/Stable
Classifier: Intended Audience :: Developers
Classifier: Topic :: Software Development :: Libraries :: Python Modules
Classifier: License :: OSI Approved :: MIT License
Classifier: Programming Language :: Python :: 3
Classifier: Programming Language :: Python :: 3 :: Only
Requires: click
Requires-Dist: click
